sp/__init__.py
sp/sp.py
spcloud-0.1.4.dist-info/METADATA
spcloud-0.1.4.dist-info/WHEEL
spcloud-0.1.4.dist-info/top_level.txt
spcloud-0.1.4.dist-info/RECORD
