Metadata-Version: 2.4
Name: SpCloud
Version: 0.1.4
Summary: A Python package for sprotect cloud compute
Home-page: https://github.com/zaixia108/SprotectCloudPython
Author: zaixia108
Author-email: zaixia108 <xvbowen2012@gmail.com>
Project-URL: homepage, https://github.com/zaixia108/SprotectCloudPython
Classifier: Programming Language :: Python :: 3
Classifier: License :: OSI Approved :: MIT License
Classifier: Operating System :: Microsoft :: Windows
Requires-Python: >=3.8
Dynamic: author
Dynamic: home-page
Dynamic: requires-python
